FIRconv/FIRconv.py
FIRconv/__init__.py
FIRconv-0.0.3.dist-info/LICENSE
FIRconv-0.0.3.dist-info/METADATA
FIRconv-0.0.3.dist-info/WHEEL
FIRconv-0.0.3.dist-info/top_level.txt
FIRconv-0.0.3.dist-info/RECORD
