Metadata-Version: 2.1
Name: FIRconv
Version: 0.0.3
Summary: Python implementation of real-time convolution for auralization
Home-page: https://github.com/davircarvalho/FIRconv
Author: Davi Carvalho
Author-email: r.davicarvalho@gmail.com
Project-URL: Bug Tracker, https://github.com/davircarvalho/FIRconv/issues
Classifier: Programming Language :: Python :: 3
Classifier: License :: OSI Approved :: MIT License
Classifier: Operating System :: OS Independent
Requires-Python: >=3.7
License-File: LICENSE
Requires-Dist: numpy
